pullbug/__init__.py
pullbug/_version.py
pullbug/bug.py
pullbug/cli.py
pullbug/messages.py
pullbug/py.typed
pullbug-6.0.0.dist-info/licenses/LICENSE
pullbug-6.0.0.dist-info/METADATA
pullbug-6.0.0.dist-info/WHEEL
pullbug-6.0.0.dist-info/entry_points.txt
pullbug-6.0.0.dist-info/top_level.txt
pullbug-6.0.0.dist-info/RECORD
